trace_goto/__init__.py
trace_goto_toanhuynh2019-0.0.1.dist-info/LICENSE
trace_goto_toanhuynh2019-0.0.1.dist-info/METADATA
trace_goto_toanhuynh2019-0.0.1.dist-info/WHEEL
trace_goto_toanhuynh2019-0.0.1.dist-info/top_level.txt
trace_goto_toanhuynh2019-0.0.1.dist-info/RECORD
