Metadata-Version: 2.1
Name: trace-goto-toanhuynh2019
Version: 0.0.1
Summary: python goto commanded implemented in trace
Home-page: https://github.com/pypa/sampleproject
Author: Toan Huynh
Author-email: toan@csinschools.io
License: UNKNOWN
Platform: UNKNOWN
Classifier: Programming Language :: Python :: 3
Classifier: License :: OSI Approved :: MIT License
Classifier: Operating System :: OS Independent
